airflow/providers/mariadb/__init__.py
airflow/providers/mariadb/get_provider_info.py
airflow/providers/mariadb/hooks/__init__.py
airflow/providers/mariadb/hooks/mariadb.py
airflow/providers/mariadb/operators/__init__.py
airflow/providers/mariadb/operators/cpimport.py
airflow/providers/mariadb/operators/mariadb.py
airflow/providers/mariadb/operators/s3.py
airflow/providers/mariadb/sensors/__init__.py
airflow/providers/mariadb/transfers/__init__.py
apache_airflow_providers_mariadb-1.0.0.dist-info/entry_points.txt
apache_airflow_providers_mariadb-1.0.0.dist-info/WHEEL
apache_airflow_providers_mariadb-1.0.0.dist-info/METADATA
apache_airflow_providers_mariadb-1.0.0.dist-info/RECORD
