Metadata-Version: 2.4
Name: apache-airflow-providers-mariadb
Version: 1.0.0
Summary: Provider package apache-airflow-providers-mariadb for Apache Airflow
Keywords: airflow-provider,mariadb,airflow,integration
Author-email: Apache Software Foundation <dev@airflow.apache.org>
Maintainer-email: Apache Software Foundation <dev@airflow.apache.org>
Requires-Python: >=3.10
Classifier: Development Status :: 5 - Production/Stable
Classifier: Environment :: Console
Classifier: Environment :: Web Environment
Classifier: Intended Audience :: Developers
Classifier: Intended Audience :: System Administrators
Classifier: Framework :: Apache Airflow
Classifier: Framework :: Apache Airflow :: Provider
Classifier: License :: OSI Approved :: Apache Software License
Classifier: Programming Language :: Python :: 3.10
Classifier: Programming Language :: Python :: 3.11
Classifier: Programming Language :: Python :: 3.12
Classifier: Programming Language :: Python :: 3.13
Classifier: Topic :: System :: Monitoring
Requires-Dist: apache-airflow>=2.5.0
Requires-Dist: mariadb>=1.1.0
Requires-Dist: apache-airflow-providers-amazon>=9.13.0
Requires-Dist: apache-airflow-providers-sftp>=5.3.0
Requires-Dist: apache-airflow-providers-ssh>=4.1.4
Requires-Dist: apache-airflow-providers-amazon ; extra == "amazon"
Project-URL: Bug Tracker, https://github.com/apache/airflow/issues
Project-URL: Changelog, https://airflow.apache.org/docs/apache-airflow-providers-mariadb/1.0.0/changelog.html
Project-URL: Documentation, https://airflow.apache.org/docs/apache-airflow-providers-mariadb/1.0.0
Project-URL: Mastodon, https://fosstodon.org/@airflow
Project-URL: Slack Chat, https://s.apache.org/airflow-slack
Project-URL: Source Code, https://github.com/apache/airflow
Project-URL: YouTube, https://www.youtube.com/channel/UCSXwxpWZQ7XZ1WL3wqevChA/
Provides-Extra: amazon
